windy_crawler/__init__.py
windy_crawler/items.py
windy_crawler/middlewares.py
windy_crawler/pipelines.py
windy_crawler/run.py
windy_crawler/settings.py
windy_crawler/spiders/__init__.py
windy_crawler/spiders/forecast_spider.py
windy_weather_crawler-1.1.dist-info/METADATA
windy_weather_crawler-1.1.dist-info/WHEEL
windy_weather_crawler-1.1.dist-info/top_level.txt
windy_weather_crawler-1.1.dist-info/RECORD
