Metadata-Version: 2.1
Name: windy-weather-crawler
Version: 1.1
Summary: A web crawler that takes input as place gives the weather forecast for 5 days
Home-page: https://github.com/SHARANTANGEDA/windy_crawler
Author: Sai Sharan Tangeda
Author-email: saisarantangeda@gmail.com
License: UNKNOWN
Platform: UNKNOWN
Classifier: Programming Language :: Python :: 3
Classifier: License :: OSI Approved :: MIT License
Classifier: Operating System :: POSIX :: Linux
Classifier: Development Status :: 4 - Beta
Classifier: Environment :: Web Environment :: Mozilla
Requires-Python: >=3.6
Requires-Dist: selenium
Requires-Dist: scrapy
Requires-Dist: tabulate
